rdf2html/__init__.py
rdf2html/translator.py
rdf2html/html/classes.html
rdf2html/html/close_header.html
rdf2html/html/data_props.html
rdf2html/html/datatypes.html
rdf2html/html/header.html
rdf2html/html/individuals.html
rdf2html/html/info.html
rdf2html/html/object.html
rdf2html-0.0.3.dist-info/LICENSE
rdf2html-0.0.3.dist-info/METADATA
rdf2html-0.0.3.dist-info/WHEEL
rdf2html-0.0.3.dist-info/top_level.txt
rdf2html-0.0.3.dist-info/RECORD
