Metadata-Version: 2.1
Name: rdf2html
Version: 0.0.3
Summary: Tool that allows to visualize ontologies in HTML using python as the base to the solution
Home-page: https://github.com/sir-onze/RDF2HTML
Author: Tiago Baptista
Author-email: tiago96baptista@gmail.com
License: UNKNOWN
Platform: UNKNOWN
Classifier: Programming Language :: Python :: 3
Classifier: License :: OSI Approved :: MIT License
Classifier: Operating System :: OS Independent
Requires-Python: >=3.6
